appdex/__init__.py
appdex/__main__.py
appdex/config.py
appdex/install.py
appdex/log.py
appdex/main.py
appdex/util.py
appdex-0.1.1.dist-info/LICENSE
appdex-0.1.1.dist-info/METADATA
appdex-0.1.1.dist-info/WHEEL
appdex-0.1.1.dist-info/entry_points.txt
appdex-0.1.1.dist-info/RECORD
