Metadata-Version: 2.1
Name: appdex
Version: 0.1.1
Summary: A highly opinionated CLI tool for installing and setting up apps on debian-based systems.
Author: Ryan Miller
Author-email: aerilym@pm.me
Requires-Python: >=3.12,<4.0
Classifier: Programming Language :: Python :: 3
Classifier: Programming Language :: Python :: 3.12
Requires-Dist: questionary (>=2.0.1,<3.0.0)
Requires-Dist: typer (>=0.12.5,<0.13.0)
